{
  "Version":"2012-10-17",
  "Id":"key-consolepolicy-3",
  "Statement":[
    {
      "Sid":"EnableIAMUserPermissions",
      "Effect":"Allow",
      "Principal":{
        "AWS":"arn:aws:iam::AWSACCOUNT:root"
      },
      "Action":"kms:*",
      "Resource":"*"
    },
    {
      "Sid":"AllowAccessForKeyAdministrators",
      "Effect":"Allow",
      "Principal":{
        "AWS":"arn:aws:iam::AWSACCOUNT:user/AWSACCOUNTPOWERUSER"
      },
      "Action":[
        "kms:Create*",
        "kms:Describe*",
        "kms:Enable*",
        "kms:List*",
        "kms:Put*",
        "kms:Update*",
        "kms:Revoke*",
        "kms:Disable*",
        "kms:Get*",
        "kms:Delete*",
        "kms:TagResource",
        "kms:UntagResource",
        "kms:ScheduleKeyDeletion",
        "kms:CancelKeyDeletion"
      ],
      "Resource":"*"
    },
    {
      "Sid":"AllowUseOfTheKey",
      "Effect":"Allow",
      "Principal":{
        "AWS":[
          "ALLPCFBLOBSTOREUSERIDS"
        ]
      },
      "Action":[
        "kms:Encrypt",
        "kms:Decrypt",
        "kms:ReEncrypt*",
        "kms:GenerateDataKey*",
        "kms:DescribeKey"
      ],
      "Resource":"*"
    },
    {
      "Sid":"AllowAttachmentOfPersistentResources",
      "Effect":"Allow",
      "Principal":{
        "AWS":[
          "ALLPCFBLOBSTOREUSERIDS"
        ]
      },
      "Action":[
        "kms:CreateGrant",
        "kms:ListGrants",
        "kms:RevokeGrant"
      ],
      "Resource":"*",
      "Condition":{
        "Bool":{
          "kms:GrantIsForAWSResource":"true"
        }
      }
    }
  ]
}
